README.md
setup.py
py_debug_inspect_utils/__init__.py
py_debug_inspect_utils/prints.py
py_debug_inspect_utils.egg-info/PKG-INFO
py_debug_inspect_utils.egg-info/SOURCES.txt
py_debug_inspect_utils.egg-info/dependency_links.txt
py_debug_inspect_utils.egg-info/not-zip-safe
py_debug_inspect_utils.egg-info/top_level.txt