Metadata-Version: 2.1
Name: py-debug-inspect-utils
Version: 0.1.0
Summary: Utils to inspect a stack to quickly debug 'magic' libraries.
Home-page: https://github.com/NyanKiyoshi/py-debug-inspect-utils/
Author: NyanKiyoshi
Author-email: hello@vanille.bid
License: UNKNOWN
Platform: UNKNOWN
Classifier: Programming Language :: Python
Classifier: Programming Language :: Python :: 3.6
Classifier: Programming Language :: Python :: 3.7
Classifier: Programming Language :: Python :: 3.8
Classifier: Intended Audience :: Developers
Classifier: Operating System :: OS Independent
Classifier: License :: Public Domain
